{"inkVersion":20,"root":[[{"->":"Quest"},["done",{"#f":5,"#n":"g-0"}],null],"done",{"Quest":[[{"#":"speaker:ชาวนา"},"^อ่า...เจ้าคือคนแปลกหน้าที่เขาลือกันเหรอ","\n","^ข้าเป็นชาวนาน่ะ ทั้งปลูกพืชผัก และเลี้ยงไก่ด้วย","\n","^แต่ตอนนี้ข้าเจอปัญหาน่ะสิ","\n","^เจ้าพอจะมีเวลาหรือไม่","\n",{"#":"speaker:quest"},"^-เควส: ไก่เจ้าปัญหา รางวัล: ???","\n","ev","str","^รับภารกิจ","/str","/ev",{"*":".^.c-0","flg":4},"ev","str","^ปฎิเสธ","/str","/ev",{"*":".^.c-1","flg":4},{"c-0":["\n",{"->":"Quest.accept"},{"#f":5}],"c-1":["\n",{"->":"Quest.reject"},{"#f":5}]}],{"accept":[[{"#":"speaker:ชาวนา"},"^ดีเลย คือข้าทำเจ้าไก่บ้านั่นหลุดไว้ที่ป่า Rachne น่ะสิ","\n","^ข้าพยายามจับมันแล้ว แต่ไม่ใช่เรื่องเลย","\n","^เจ้าไปจับมาให้ข้อหน่อยนะ","\n","ev","str","^ได้เลย","/str","/ev",{"*":".^.c-0","flg":4},{"c-0":["\n",{"#":"quest:47"},"done","done",{"#f":5}]}],{"#f":1}],"reject":[{"#":"speaker:ชาวนา"},{"#":"event:chickReject"},"^งั้นเหรอ...","\n","^เอาเถอะ ข้าคงต้องหาวิธีจัดการเอง","\n","^แต่เจ้าคงอดได้สิ่งที่น่าสนใจไปแล้วล่ะ","\n","done","done",{"#f":1}],"#f":1}],"#f":1}],"listDefs":{}}