{"inkVersion":20,"root":[["\n",{"->":"Quest"},["done",{"#f":5,"#n":"g-0"}],null],"done",{"Quest":[["ev",{"VAR?":"refuseGuard"},"/ev",[{"->":".^.b","c":true},{"b":[{"->":"Refuse"},{"->":".^.^.^.4"},null]}],"nop","\n",{"#":"speaker:ยาม"},"^สวัสดี...พอดีช่วงนี้ข้าไม่ค่อยสบายเลย","\n","^เหนื่อยมากเลยล่ะ...","\n","^ข้าอยากให้ใครสักคนมาช่วยแบ่งเบาภาระของข้าจังเลย","\n","ev","str","^ให้ช่วยไหม","/str","/ev",{"*":".^.c-0","flg":4},"ev","str","^ปฎิเสธ","/str","/ev",{"*":".^.c-1","flg":4},{"c-0":["\n",{"->":".^.^.g-0"},{"#f":5}],"c-1":["\n",{"#":"speaker:ยาม"},"^เชอะ!!","\n","ev",true,"/ev",{"VAR=":"refuseGuard","re":true},"done",{"->":".^.^.g-0"},{"#f":5}],"g-0":["^จะดีหรอ...ข้าเห็นเจ้าดูเหนื่่อยจากการที่ไปช่วยคนในเมืองมานะ","\n","ev","str","^ไม่เป็นไรให้ข้าช่วยเถอะ","/str","/ev",{"*":".^.c-2","flg":4},{"c-2":["\n",{"->":".^.^.^.g-1"},{"#f":5}],"#f":5}],"g-1":["^ถ้าอย่างนั้น...เจ้าสนใจงานไหนล่ะ ค่าตอบแทนดีนะ","\n",{"#":"speaker:quest"},"^เลือกภารกิจ","\n","ev","str","^รูปแห่งความทรงจำ","/str","/ev",{"*":".^.c-3","flg":4},"ev","str","^กำจัด Skeleton","/str","/ev",{"*":".^.c-4","flg":4},{"c-3":["\n",{"#":"speaker:quest"},"^- เควส: รูปแห่งความทรงจำ รางวัล: 1500 MP","\n",{"#":"quest:51"},"done",{"#f":5}],"c-4":["\n",{"#":"speaker:quest"},"^- เควส: กำจัด<color=#FFBD39>Skeleton</color>จำนวน 10 ตัว ที่<color=#FF7272>Cave</color> รางวัล: 500 MP และสกิลสุดพิเศษ","\n",{"#":"quest:53"},"done",{"#f":5}],"#f":5}]}],{"#f":1}],"Refuse":[{"#":"speaker:ยาม"},"^มีอะไร!!","\n","^ถ้าไม่มีอะไรก็ไปทำการทำงานของเจ้าซะ","\n","^ออกไป!!","\n","done","done",{"#f":1}],"global decl":["ev",false,{"VAR=":"sataAskToJoin"},false,{"VAR=":"metSata"},false,{"VAR=":"readOP"},false,{"VAR=":"acceptWebsterQ"},"str","^","/str",{"VAR=":"name"},false,{"VAR=":"toldName"},false,{"VAR=":"usePotionComplete"},false,{"VAR=":"cainAskToGo"},false,{"VAR=":"cainAskToGoAgain"},false,{"VAR=":"turnbacktime"},false,{"VAR=":"refuseMerchant"},false,{"VAR=":"refuseGuard"},"/ev","end",null],"#f":1}],"listDefs":{}}